esp_idf_ldgen/__init__.py
esp_idf_ldgen/__main__.py
esp_idf_ldgen/ldgen.py
esp_idf_ldgen/libldgen/__init__.py
esp_idf_ldgen/libldgen/entity.py
esp_idf_ldgen/libldgen/fragments.py
esp_idf_ldgen/libldgen/generation.py
esp_idf_ldgen/libldgen/ldgen_common.py
esp_idf_ldgen/libldgen/linker_script.py
esp_idf_ldgen/libldgen/output_commands.py
esp_idf_ldgen/libldgen/sdkconfig.py
esp_idf_ldgen-0.1.0.dist-info/LICENSE
esp_idf_ldgen-0.1.0.dist-info/METADATA
esp_idf_ldgen-0.1.0.dist-info/WHEEL
esp_idf_ldgen-0.1.0.dist-info/top_level.txt
esp_idf_ldgen-0.1.0.dist-info/RECORD
