Metadata-Version: 2.1
Name: esp-idf-ldgen
Version: 0.1.0
Summary: Linker Script Generator
Home-page: https://github.com/espressif/esp-idf-ldgen
Author: Espressif Systems
Author-email: 
Keywords: espressif,embedded,linker,build
Classifier: Development Status :: 4 - Beta
Classifier: Intended Audience :: Developers
Classifier: Natural Language :: English
Classifier: Environment :: Console
Classifier: Topic :: Software Development :: Embedded Systems
Classifier: License :: OSI Approved :: Apache Software License
Classifier: Programming Language :: Python :: 3.7
Classifier: Programming Language :: Python :: 3.8
Classifier: Programming Language :: Python :: 3.9
Classifier: Programming Language :: Python :: 3.10
Classifier: Programming Language :: Python :: 3.11
Classifier: Operating System :: POSIX
Classifier: Operating System :: Microsoft :: Windows
Classifier: Operating System :: MacOS :: MacOS X
Requires-Python: >=3.7
License-File: LICENSE
Requires-Dist: pyparsing (>=3.0.3)
Requires-Dist: kconfiglib (>=13.7.1)
